aquaagent/__init__.py
aquaagent/agent.py
aquaagent/modules/analyzer.py
aquaagent/modules/auto_optimizer.py
aquaagent/modules/data_handler.py
aquaagent/modules/imputation_engine.py
aquaagent/modules/ml_selector.py
aquaagent/modules/model_explainer.py
aquaagent/modules/reporter.py
aquaagent/modules/visualizer.py
aquaagent-0.1.0.dist-info/licenses/LICENSE
aquaagent-0.1.0.dist-info/METADATA
aquaagent-0.1.0.dist-info/WHEEL
aquaagent-0.1.0.dist-info/top_level.txt
aquaagent-0.1.0.dist-info/RECORD
