Metadata-Version: 2.4
Name: AquaAgent
Version: 0.1.0
Summary: An autonomous and interactive AI agent for intelligent water quality analysis and reporting.
Home-page: https://github.com/TyMill/-AquaAgent
Author: Tymoteusz Miller
Author-email: Tymoteusz Miller <me@tymoteuszmiller.dev>
License: MIT
Requires-Python: >=3.8
License-File: LICENSE
Requires-Dist: pandas
Requires-Dist: numpy
Requires-Dist: matplotlib
Requires-Dist: seaborn
Requires-Dist: scikit-learn
Requires-Dist: xgboost
Requires-Dist: optuna
Requires-Dist: shap
Requires-Dist: lime
Requires-Dist: plotly
Requires-Dist: jinja2
Requires-Dist: tensorflow>=2.10
Requires-Dist: keras>=2.10
Dynamic: license-file
